.gitignore
.travis.yml
LICENSE
Makefile
README.md
requirements.txt
setup.py
documentation/API.md
rootmeapi/RootMeAPI.py
rootmeapi/__init__.py
rootmeapi.egg-info/PKG-INFO
rootmeapi.egg-info/SOURCES.txt
rootmeapi.egg-info/dependency_links.txt
rootmeapi.egg-info/top_level.txt
rootmeapi/types/Author.py
rootmeapi/types/Challenge.py
rootmeapi/types/Solution.py
rootmeapi/types/__init__.py